segmenthee/__init__.py
segmenthee/cart_api.py
segmenthee/config.py
segmenthee/parser_api.py
segmenthee/shop.py
segmentheepy_book-1.0.0.dist-info/METADATA
segmentheepy_book-1.0.0.dist-info/WHEEL
segmentheepy_book-1.0.0.dist-info/top_level.txt
segmentheepy_book-1.0.0.dist-info/RECORD
